mdx_inline_graphviz.py
markdown_inline_graphviz-1.0.dist-info/DESCRIPTION.rst
markdown_inline_graphviz-1.0.dist-info/METADATA
markdown_inline_graphviz-1.0.dist-info/RECORD
markdown_inline_graphviz-1.0.dist-info/WHEEL
markdown_inline_graphviz-1.0.dist-info/metadata.json
markdown_inline_graphviz-1.0.dist-info/top_level.txt
