Metadata-Version: 2.0
Name: markdown-inline-graphviz
Version: 1.0
Summary: Render inline graphs with Markdown and Graphviz
Home-page: https://github.com/sprin/markdown-inline-graphviz
Author: Steffen Prince
Author-email: steffen@sprin.io
License: MIT
Platform: UNKNOWN
Classifier: Development Status :: 5 - Production/Stable
Classifier: Intended Audience :: Developers
Classifier: Topic :: Documentation
Classifier: Topic :: Text Processing
Classifier: License :: OSI Approved :: MIT License
Classifier: Programming Language :: Python :: 2
Classifier: Programming Language :: Python :: 2.7
Classifier: Programming Language :: Python :: 3
Classifier: Programming Language :: Python :: 3.4
Classifier: Programming Language :: Python :: 3.5
Requires-Dist: Markdown (>=2.3.1)
